randonneur_data/__init__.py
randonneur_data/data/agribalyse-3.1.1-delete-aggregated-ecoinvent.gz
randonneur_data/data/agribalyse-3.1.1-ecoinvent-3.10-biosphere-manual-matches.json
randonneur_data/data/agribalyse-3.1.1-restore-simapro-ecoinvent-names.gz
randonneur_data/data/agribalyse-3.1.1-unlinked-ecoinvent-3.8-biosphere.json
randonneur_data/data/agrifootprint-2022-delete-aggregated-ecoinvent.json
randonneur_data/data/agrifootprint-2022-restore-simapro-ecoinvent-names.json
randonneur_data/data/agrifootprint-biosphere-ecoinvent-3.10-biosphere.gz
randonneur_data/data/agrifootprint-biosphere-ecoinvent-3.8-biosphere.gz
randonneur_data/data/ecoinvent-2.2-biosphere-context-ecoinvent-3.0-biosphere-context.json
randonneur_data/data/ecoinvent-2.2-biosphere-ecoinvent-3.0-biosphere.json
randonneur_data/data/ecoinvent-3.10.1-biosphere-EF-3.1-biosphere.gz
randonneur_data/data/ecoinvent-3.10.1-biosphere-ecoinvent-3.11-biosphere.json
randonneur_data/data/ecoinvent-3.10.1-cutoff-ecoinvent-3.11-cutoff.gz
randonneur_data/data/ecoinvent-3.11-biosphere-EF-3.1-biosphere.gz
randonneur_data/data/ecoinvent-3.11-cutoff-ecoinvent-3.12-cutoff.gz
randonneur_data/data/ecoinvent-3.7.1-cutoff-ecoinvent-3.8-cutoff.json
randonneur_data/data/ecoinvent-3.8-biosphere-ecoinvent-3.9-biosphere.gz
randonneur_data/data/ecoinvent-3.8-biosphere-ecoinvent-3.9-biosphere.json
randonneur_data/data/ecoinvent-3.8-cutoff-ecoinvent-3.9-cutoff.gz
randonneur_data/data/ecoinvent-3.9.1-biosphere-EF-3.1-biosphere.gz
randonneur_data/data/ecoinvent-3.9.1-biosphere-ecoinvent-3.10-biosphere.gz
randonneur_data/data/ecoinvent-3.9.1-cutoff-ecoinvent-3.10-cutoff.gz
randonneur_data/data/generic-brightway-unit-conversions.json
randonneur_data/data/generic-brightway-units-normalization.json
randonneur_data/data/registry.json
randonneur_data/data/simapro-9-ecoinvent-3-context.json
randonneur_data/data/simapro-9-ecoinvent-3-water-slash-m3.gz
randonneur_data/data/simapro-9-ecoinvent-3.8-biosphere-manual-matches.json
randonneur_data-0.7.1.dist-info/licenses/LICENSE
randonneur_data-0.7.1.dist-info/METADATA
randonneur_data-0.7.1.dist-info/WHEEL
randonneur_data-0.7.1.dist-info/top_level.txt
randonneur_data-0.7.1.dist-info/RECORD
